README.rst
setup.py
ecowitt_dev/__init__.py
ecowitt_dev/__main__.py
ecowitt_dev/ecowitt.py
ecowitt_dev/fake_client.py
ecowitt_dev/sensor_map.py
ecowitt_dev.egg-info/PKG-INFO
ecowitt_dev.egg-info/SOURCES.txt
ecowitt_dev.egg-info/dependency_links.txt
ecowitt_dev.egg-info/not-zip-safe
ecowitt_dev.egg-info/requires.txt
ecowitt_dev.egg-info/top_level.txt