Metadata-Version: 1.1
Name: ecowitt-dev
Version: 0.1.0
Summary: Module to communicate with the Ecowitt procotol
Home-page: https://github.com/garbled1/pyecowitt
Author: Ecowitt
Author-email: admin@ecowitt.net
License: Apache 2.0
Platform: UNKNOWN
Classifier: Development Status :: 4 - Beta
Classifier: Intended Audience :: Developers
Classifier: License :: OSI Approved :: Apache Software License
Classifier: Programming Language :: Python :: 3 :: Only
Classifier: Topic :: Software Development :: Libraries :: Python Modules
